{
    "Absolute": "Absoluto",
    "AccessRestrictedTryAgainLater": "O acceso está restrinxido actualmente. Por favor, intenteo máis tarde.",
    "Actor": "Actor",
    "Add": "Engadir",
    "AddToCollection": "Engadir á coleción",
    "AddToFavorites": "Engadir a favoritos",
    "AddToPlayQueue": "Engadir á coda de reprodución",
    "AddToPlaylist": "Engadir á lista de reprodución",
    "AddedOnValue": "Engadido {0}",
    "AdditionalNotificationServices": "Navega o catálogo de plugins para instalar servicios de notificación adicionáis.",
    "AgeValue": "({0} anos)",
    "AirDate": "Data de emisión",
    "Aired": "Emitido",
    "Album": "Álbume",
    "AlbumArtist": "Artista do Álbume",
    "Albums": "Álbumes",
    "Alerts": "Avisos",
    "All": "Todo",
    "AllChannels": "Todos os canais",
    "AllComplexFormats": "Todos os formatos complexos (ASS, SSA, VobSub, PGS, SUB, IDX, …)",
    "AllEpisodes": "Todos os episodios",
    "AllLanguages": "Todas as linguas",
    "AllLibraries": "Todas as bibliotecas",
    "AllowFfmpegThrottling": "Acelerar Transcodificacións",
    "AllowMediaConversion": "Permitir a conversión dos medios",
    "AllowMediaConversionHelp": "Permitir ou denegar aceso á función de conversión de medios.",
    "AllowOnTheFlySubtitleExtraction": "Permitir extracción de subtítulos sobre a marcha",
    "AllowRemoteAccess": "Permitir conexións remotas a este servidor",
    "AllowRemoteAccessHelp": "Se está desmarcado, todas as conexions remotas serán bloqueadas.",
    "AllowedRemoteAddressesHelp": "Lista separada por comas das direcións IP ou entradas de máscara de rede para redes ás que se permitirá conectar remotamente. En branco, calquera direción remota será permitida.",
    "AlwaysPlaySubtitles": "Reproducir sempre",
    "AlwaysPlaySubtitlesHelp": "Os subtítulos correspondentes ó idioma de preferencia serán cargados independentemente do idioma do audio.",
    "AnyLanguage": "Calquera Lingua",
    "Anytime": "Calquer Momento",
    "ApiKeysCaption": "Lista das claves API activadas neste momento",
    "AroundTime": "Sobre {0}",
    "Artist": "Artista",
    "Artists": "Artistas",
    "AsManyAsPossible": "Tantos como sexa posible",
    "Ascending": "Ascendentemente",
    "AskAdminToCreateLibrary": "Preguntar a un administrador para crear a libraría.",
    "AspectRatio": "Radio de aspecto",
    "Audio": "Audio",
    "Authorize": "Autorizar",
    "Auto": "Auto",
    "Banner": "Cabeceira",
    "BirthDateValue": "Nacido: {0}",
    "BirthLocation": "Lugar de nacemento",
    "BirthPlaceValue": "Lugar de nacemento: {0}",
    "Blacklist": "Lista negra",
    "Books": "Libros",
    "Browse": "Explorar",
    "ButtonCast": "Transmitir contido multimedia a un dispositivo",
    "ButtonSend": "Enviar",
    "ButtonShutdown": "Apagar",
    "ButtonSplit": "Dividir",
    "ButtonStart": "Iniciar",
    "ButtonStop": "Deter",
    "ButtonSubmit": "Enviar",
    "ButtonSyncPlay": "SyncPlay",
    "ButtonTrailer": "Tráiler",
    "ButtonUninstall": "Desinstalar",
    "ButtonWebsite": "Sitio web",
    "Categories": "Categorías",
    "Channels": "Canles",
    "Collections": "Colecións",
    "Composer": "Compositor",
    "Connect": "Conectar",
    "Continuing": "Continuar",
    "Default": "Por defecto",
    "Delete": "Eliminar",
    "Descending": "Descendente",
    "Desktop": "Escritorio",
    "Director": "Director",
    "Disc": "Disco",
    "Disconnect": "Desconectar",
    "Display": "Visualización",
    "Down": "Abaixo",
    "Download": "Descargar",
    "Edit": "Editar",
    "Ended": "Finalizado",
    "Episodes": "Episodios",
    "Extras": "Extras",
    "FastForward": "Avanzar rápido",
    "Favorite": "Favorito",
    "Favorites": "Favoritos",
    "Features": "Características",
    "File": "Arquivo",
    "Filters": "Filtros",
    "Folders": "Cartafoles",
    "Friday": "Venres",
    "General": "Xeral",
    "Genres": "Xéneros",
    "Guide": "Guía",
    "GuideProviderLogin": "Iniciar sesión",
    "HeaderActivity": "Actividade",
    "HeaderAdmin": "Administración",
    "HeaderAlbumArtists": "Artistas do Album",
    "HeaderAlert": "Alerta",
    "HeaderApp": "Aplicación",
    "HeaderBranding": "Apariencia de marca",
    "HeaderContinueWatching": "Seguir mirando",
    "HeaderDevices": "Dispositivos",
    "HeaderError": "Erro",
    "HeaderIdentification": "Identificación",
    "HeaderInstall": "Instalar",
    "HeaderLibraries": "Bibliotecas",
    "HeaderMedia": "Medios",
    "HeaderNavigation": "Navegación",
    "HeaderPassword": "Contrasinal",
    "HeaderPaths": "Rutas",
    "HeaderScenes": "Escenas",
    "HeaderSeasons": "Temporada",
    "HeaderStatus": "Estado",
    "HeaderTracks": "Pistas",
    "HeaderTuners": "Sintonizadores",
    "HeaderUser": "Usuario",
    "HeaderUsers": "Usuarios",
    "HeaderVideos": "Vídeos",
    "HeaderYears": "Anos",
    "Help": "Axuda",
    "Hide": "Ocultar",
    "Home": "Inicio",
    "Horizontal": "Horizontal",
    "Identify": "Identificar",
    "Images": "Imaxes",
    "Items": "Elementos",
    "Kids": "Infantil",
    "LabelAlbum": "Álbum:",
    "LabelArtists": "Artistas:",
    "LabelBitrate": "Bitrate:",
    "LabelCache": "Caché:",
    "LabelCancelled": "Cancelado",
    "LabelChannels": "Canles:",
    "LabelCollection": "Coleccións:",
    "LabelCountry": "Países:",
    "LabelEvent": "Evento:",
    "Movies": "Películas",
    "MusicVideos": "Vídeos Musicais",
    "OptionBluray": "BD",
    "Photos": "Fotos",
    "Playlists": "Listas de reproducción",
    "Shows": "Programas",
    "Songs": "Cancións",
    "Sync": "Sincronizar",
    "ValueSpecialEpisodeName": "Especial - {0}"
}
