{
    "Album": "Цомог",
    "Albums": "Цомгууд",
    "Artist": "Жүжигчин",
    "Artists": "Зураачуд",
    "BirthDateValue": "Эхэлсэн: {0}",
    "Books": "Номууд",
    "ButtonCancel": "Цуцлах",
    "ButtonSyncPlay": "SyncPlay",
    "ButtonTogglePlaylist": "Тоглуулах жагсаалт",
    "ButtonTrailer": "Трейлер",
    "Bwdif": "BWDIF",
    "CancelRecording": "Бичлэгийг цуцлах",
    "CancelSeries": "Цувралыг цуцлах",
    "Collections": "Багц",
    "ContinueWatching": "Үргэлжлүүлэн үзэх",
    "CriticRating": "Шүүмжлэгчдийн үнэлгээ",
    "DashboardVersionNumber": "Хувилбар: {0}",
    "DateAdded": "Өдөр нэмэх",
    "Desktop": "Компьютер",
    "DisablePlugin": "Идэвхгүй болгох",
    "Episodes": "Бүлгүүд",
    "Favorite": "Дуртай",
    "Favorites": "Дуртай",
    "Filter": "Шүүлтүүр",
    "Filters": "Шүүлтүүрүүд",
    "General": "Ерөнхий",
    "Genre": "Төрөл зүйл",
    "Genres": "Төрөл зүйл",
    "HeaderCancelRecording": "Бичлэгийг цуцлах",
    "HeaderContinueWatching": "Үргэлжлүүлэн үзэх",
    "HeaderInstantMix": "Шуурхай холимог",
    "HeaderOnNow": "Одоо асаах",
    "HeaderPlayAll": "Бүгдийг тоглуулах",
    "HeaderSeasons": "Үе",
    "HeaderSyncPlayPlaybackSettings": "Тоглуулах",
    "HeaderVideos": "Видеонууд",
    "InstantMix": "Шуурхай холимог",
    "LabelAlbum": "Цомог",
    "LabelChromecastVersion": "Chromecast Хувилбар",
    "LabelCollection": "Багц",
    "LabelCriticRating": "Шүүмжлэгчдийн үнэлгээ",
    "LabelDateAdded": "Өдөр нэмэх",
    "LabelName": "Нэр",
    "LabelPlaylist": "Тоглуулах жагсаалт",
    "LabelRecord": "Бичлэг",
    "LabelVersion": "Хувилбар",
    "MarkPlayed": "Тоглосон гэж тэмдэглэсэн",
    "MessageSyncPlayDisabled": "SyncPlay идэвхгүй.",
    "Mobile": "Үүрэн",
    "Monday": "Даваа",
    "Movie": "Кино",
    "Movies": "Кино",
    "Name": "Нэр",
    "Never": "Боломжгүй",
    "NextUp": "Дараах",
    "No": "Үгүй",
    "None": "Байхгүй",
    "Option3D": "3D",
    "OptionBluray": "BD",
    "OptionCriticRating": "Шүүмжлэгчдийн үнэлгээ",
    "OptionDateAdded": "Өдөр нэмэх",
    "OptionDvd": "DVD",
    "OptionIsHD": "HD",
    "OptionIsSD": "SD",
    "OptionProtocolHttp": "HTTP",
    "OptionSpecialEpisode": "Онцгой",
    "Other": "Бусад",
    "People": "Хүмүүс",
    "Play": "Тоглуулах",
    "Playlists": "Тоглуулах жагсаалт",
    "RecommendationBecauseYouWatched": "Та үзсэн болохоор {0}",
    "RecommendationDirectedBy": "Найруулсан {0}",
    "Record": "Бичлэг",
    "RecordSeries": "Цувралыг бичих",
    "RecordingCancelled": "Бичлэгийг цуцаллаа.",
    "Recordings": "Бичлэгүүд",
    "Saturday": "Бямба гариг",
    "Search": "Хайх",
    "Season": "Үе",
    "Series": "Цуврал",
    "Settings": "Тохиргоо",
    "Songs": "Дуунууд",
    "Sunday": "Ням гараг",
    "TV": "ТВ-ийн багц",
    "TabLatest": "Сүүлийн үеийн",
    "TabOther": "Бусад",
    "TabUpcoming": "Дээшээ ирж байна",
    "Thursday": "Пүрэв гараг",
    "TitlePlayback": "Тоглуулах",
    "Tuesday": "Мягмар гараг",
    "TypeOptionPluralBook": "Номууд",
    "TypeOptionPluralEpisode": "Бүлгүүд",
    "TypeOptionPluralMovie": "Кино",
    "TypeOptionPluralSeason": "Үе",
    "TypeOptionPluralVideo": "Видеонууд",
    "Watched": "Үзсэн",
    "Yes": "Тийм"
}
